whatweet.py
whatweet-0.0.1.dist-info/METADATA
whatweet-0.0.1.dist-info/WHEEL
whatweet-0.0.1.dist-info/entry_points.txt
whatweet-0.0.1.dist-info/top_level.txt
whatweet-0.0.1.dist-info/RECORD
