Metadata-Version: 2.1
Name: whatweet
Version: 0.0.1
Summary: Various analyses of tweet content
Home-page: https://github.com/hnt-series00/whatweet
Author: Hinata Serizawa
Author-email: s1922065@stu.musashino-u.ac.jp
License: UNKNOWN
Project-URL: Bug Tracker, https://github.com/hnt-series00/whatweet
Platform: UNKNOWN
Classifier: License :: OSI Approved :: MIT License
Classifier: Programming Language :: Python :: 3
Requires-Python: >=3.9
